{"chunk_definitions":[{"chunk_id":"csetup_chunk","expansion_state":0,"options":[],"row":21,"row_count":1,"visible":true},{"chunk_id":"chsi0wodo0za2","expansion_state":0,"options":[],"row":31,"row_count":1,"visible":true},{"chunk_id":"clsiniv6bkmkx","expansion_state":0,"options":[],"row":51,"row_count":1,"visible":true},{"chunk_id":"c0fns572ydurr","expansion_state":0,"options":[],"row":75,"row_count":1,"visible":true},{"chunk_id":"caikn0yhsktpq","expansion_state":0,"options":[],"row":86,"row_count":1,"visible":true},{"chunk_id":"chi9970ffpfz9","expansion_state":0,"options":[],"row":123,"row_count":1,"visible":true},{"chunk_id":"csll09pb32fjr","expansion_state":0,"options":[],"row":128,"row_count":1,"visible":true}],"doc_write_time":1588740518.85519}
